tests/__init__.py
tests/test_vault.py
vaulter/__init__.py
vaulter/core.py
vaulter/crypto.py
vaulter/exceptions.py
vaulter/utils.py
vaulter-1.0.0.dist-info/licenses/LICENSE
vaulter-1.0.0.dist-info/METADATA
vaulter-1.0.0.dist-info/WHEEL
vaulter-1.0.0.dist-info/top_level.txt
vaulter-1.0.0.dist-info/RECORD
